grzctl/__init__.py
grzctl/cli.py
grzctl/py.typed
grzctl/commands/__init__.py
grzctl/commands/archive.py
grzctl/commands/clean.py
grzctl/commands/consent.py
grzctl/commands/decrypt.py
grzctl/commands/download.py
grzctl/commands/list_submissions.py
grzctl/commands/pruefbericht.py
grzctl/commands/report.py
grzctl/commands/db/__init__.py
grzctl/commands/db/cli.py
grzctl/commands/db/sync.py
grzctl/commands/db/tui.css
grzctl/commands/db/tui.py
grzctl/models/__init__.py
grzctl/models/config.py
grzctl/models/db.py
grzctl/models/pruefbericht.py
grzctl-1.4.0.dist-info/METADATA
grzctl-1.4.0.dist-info/WHEEL
grzctl-1.4.0.dist-info/entry_points.txt
grzctl-1.4.0.dist-info/RECORD
